Workbook

Sheet PersonalInfo
A1: NOTE: This form is not the same as last year's. Please don't copy / paste last year's answers. Taking 30 minutes to read and properly fill this out will save hours of back and forth via email and dramatically reduce the risk of an audit letter from the IRS due to not including something in your return that you should have included.
A2: Planned Filing Status | E2: Filing Status | H2: Yes | K2: Not In US | O2: Version | P2: TY2024.1.0
A3: Expected Filing Status | E3: 1 = Single | H3: No | K3: Alabama
A4: Taxpayer Information | B4: Taxpayer | C4: Spouse | E4: 2 = Married, Filing Jointly | K4: Alaska
A5: First Name & Middle Initial | E5: 3 = Married, Filing Separately | K5: Arizona
A6: Last Name | E6: 4 = Head of Household | K6: Arkansas
A7: Title / Suffix | E7: 5 = Qualified Widow | K7: California
A8: On 12/31, what was your marital status? | K8: Colorado
A9: SSN | K9: Connecticut
A10: Date of Birth (mm/dd/yyyy) | E10: Divorced | K10: Hawaii
A11: Occupation | E11: Married | K11: Florida
A12: Contact Phone Number
A13: Form of Id and Location of Issuance | K13: Connecticut
A14: ID Number | K14: Connecticut
A15: ID Issue Date | K15: Connecticut
A16: ID Expiration Date | K16: Connecticut
A17: NY State Document Number (if it's a NY Driver's License) | E17: Single | K17: Delaware
A18: Address Information | E18: Married | K18: Idaho
A19: Street Address | E19: Divorced | K19: Illinois
A20: Apartment / Unit Number | E20: Widowed | K20: Indiana
A21: City | E21: Legally Separated | K21: Iowa
A22: State | K22: Kansas
A23: Zip | K23: Kentucky
A24: County
A25: Resident of what state as of 12/31?
A26: If you moved during the year, list all states where you resided during the tax year and the date you moved out of that state | K26: Louisiana
A27: Dependent Information | B27: Dependent 1 | C27: Dependent 2 | K27: Michigan
A28: First Name & Middle Initial | K28: Minnesota
A29: Last Name | B29: =IF($B$6="","",IF(B28="","",$B$6)) | C29: =IF($B$6="","",IF(C28="","",$B$6)) | K29: Mississippi
A30: Suffix | K30: Missouri
A31: Date of Birth (mm/dd/yyyy) | K31: Montana
A32: SSN | K32: Nebraska
A33: Relationship to Taypayer | K33: Nevada
A34: Months Lived At Home This Year | K34: New Hampshire
A35: What was your total qualified childcare cost for this dependent? | K35: New Jersey
A36: Did this dependent have any post-secondary tuition expenses? | K36: New Mexico
A37: Is This Dependent ove age 18 and Disabled? | K37: New York
A38: Is This Dependent over age 19 and a Student? | K38: North Carolina
A39: Dependent Information | B39: Dependent 3 | C39: Dependent 4 | K39: North Dakota
A40: First Name & Middle Initial | K40: Ohio
A41: Last Name | B41: =IF($B$6="","",IF(B40="","",$B$6)) | C41: =IF($B$6="","",IF(C40="","",$B$6)) | K41: Oklahoma
A42: Suffix | K42: Oregon
A43: Date of Birth (mm/dd/yyyy) | K43: Pennsylvania
A44: SSN | K44: Rhode Island
A45: Relationship to Taypayer | K45: South Carolina
A46: Months Lived At Home This Year | K46: South Dakota
A47: What was your total qualified childcare cost for this dependent? | K47: Tennessee
A48: Did this dependent have any post-secondary tuition expenses? | K48: Texas
A49: Is This Dependent ove age 18 and Disabled? | K49: Utah
A50: Is This Dependent over age 19 and a Student? | K50: Vermont
A51: Dependent Information | B51: Dependent 5 | C51: Dependent 6 | K51: Virginia
A52: First Name & Middle Initial | K52: Washington
A53: Last Name | B53: =IF($B$6="","",IF(B52="","",$B$6)) | C53: =IF($B$6="","",IF(C52="","",$B$6)) | K53: West Virginia
A54: Suffix | K54: Wisconsin
A55: Date of Birth (mm/dd/yyyy) | K55: Wyoming
A56: SSN
A57: Relationship to Taypayer
A58: Months Lived At Home This Year
A59: What was your total qualified childcare cost for this dependent?
A60: Did this dependent have any post-secondary tuition expenses?
A61: Is This Dependent ove age 18 and Disabled?
A62: Is This Dependent over age 19 and a Student?
A63: Dependent Information | B63: Dependent 7 | C63: Dependent 8
A64: First Name & Middle Initial
A65: Last Name | B65: =IF($B$6="","",IF(B64="","",$B$6)) | C65: =IF($B$6="","",IF(C64="","",$B$6))
A66: Suffix
A67: Date of Birth (mm/dd/yyyy)
A68: SSN
A69: Relationship to Taypayer
A70: Months Lived At Home This Year
A71: What was your total qualified childcare cost for this dependent?
A72: Did this dependent have any post-secondary tuition expenses?
A73: Is This Dependent ove age 18 and Disabled?
A74: Is This Dependent over age 19 and a Student?
A75: END OF SHEET 1 -> CONTINUE TO Questionnaire Tab

Sheet Questionnaire
A1: NOTE: This form is not the same as last year's. Please don't copy / paste last year's answers. Taking 30 minutes to read and properly fill this out will save hours of back and forth via email and dramatically reduce the risk of an audit letter from the IRS due to not including something in your return that you should have included. There were MANY tax changes in 2025 due to the One Big Beautiful Bill. Those who took the standard deduction in 2024 may be able to itemize in 2025. Don't assume you can't unless you know for certain.
A2: Indicate yes/no response with 'x' in the appropriate cell. Provide additional detail in the Comment field as required for each question.
A3: Yes | B3: No | C3: Comment | D3: Question | E3: Links to More Info
A4: Personal Information
D5: I have read the statement in Orange above and agree that I will not copy my answers from last year. If you can't answer "Yes" to this question, please contact us.
D6: If you are due any refunds would you like them to be direct deposited? If yes, list bank name, routing number, account number, and checking or savings in Comment or indicate "Same As Last Year"
D7: If you owe any tax, would you like the amount to be directly debited from your bank account? If yes, list bank name, routing number, account number, and checking or savings in Comment or indicate "Same As Last Year". Note: withdrawal date can be set by you and nothing will be filed before your approval / time to prepare for withdrawal.
D8: Do you want to allocate $3 to the Presidential Election Campaign Fund?
D9: Does your spouse (if applicable) want to allocate $3 to the Presidential Election Campaign Fund?
D10: Did your marital status change during the year? (If yes, indicate from what to what in Comment. If you got divorced or married, please indicate the date of the status change in the Comment as well.
D11: Did your address change during the year? (If yes, list previous address in Comment)
D12: Did you change your state of residence during the year? (If yes, list date you established residence in the new state). Can skip this if you entered this info on the PersonalInfo tab for all states.
D13: Did you have health insurance for you, your spouse, and all dependents for the entire year? Note: The Federal penalty for not having health insurance remained at $0 for 2025, but some states still impose penalties, so please answer the question anyway. If you answer no and it matters for your state, we'll contact you for more info.
D14: Did you enroll in a health plan through your (or your spouse's) employer? If yes, please include Form 1095-B (from insurer, who might be your employer in some cases) and Form 1095-C (from employer) if you received them. Note that the deadline to send these forms may be extended again for tax year 2025 so you may not receive them before filing. We can work around this if you marked "Yes" to the previous question about having insurance for the entire year or if maintaining health coverage is not an issue in your state. MA residents, please also include Form MA-1099-HC | E14: Link to IRS Q&A
D15: Did you enroll in a health plan through a health insurance marketplace (e.g. ACA or Obamacare exchange)? If yes, please include Form 1095-A, which would have been sent to you by the exchange. Unlike 1095B/C, 1095-A is mandatory if for your tax prep if you purchased insurance through an ACA exchange.
D16: Have you created an online tax account with the IRS? Please check Yes if you and/or your spouse (if applicable) has created a tax account. | E16: Link To IRS Online Account
D17: Did you work in any states other than your 12/31 state of residency? (If yes, list the states and provide a breakdown of your earnings by state, unless it is shown on your W-2(s)).
D18: Have you received an Identity Protection PIN (IPPIN) from the IRS (most people haven't, so don't worry if you don't know what this is). If you have, this number is required to EFILE. Please include the IPPIN in the Comment and who it pertains to (taxpayer, spouse, or a child) or include the letter the IRS sent to you with your tax docs. If you signed up for this program, you need a new number every year. | E18: Link to IPPIN Info | F18: Link To IRS Online Account
A19: Dependants
D20: Were there any changes to dependents this year? (If yes, describe in Comment). If you're not sure whether someone is your dependent or not, the link to the right will walk you through a Q/A to determine it. | E20: Link to IRS Dependent Info
D21: Were any of your unmarried children who might be claimed as dependents 19 years of age or older at the end of last year? (If yes, indicate who in Comment)
D22: Did you incur any qualified childcare expenses AND, did you (and your spouse if you're married) have earned income? If yes, please complete the QualifedChildcare tab or provide additional statements with ALL equivalent information. Include childcare costs even if they were reimbursed by a dependent care flexibile spending account (FSA) as that reimbursement must be justified on your return | E22: Link to IRS Pub 503
D23: Did you have any children under age 19 or full-time students under age 24 at the end of the year with investment income in excess of $1350?
D24: Are you planning on opening a “Trump account” for one or more of your dependents as part of your 2025 tax filing? Note: accounts can't be opened until July 2026 and don't have to be opened as part of tax filing. You can also do so via an online portal that will be available by summer 2026. | E24: Link to Details
D25: Did any of your dependents work or earn enough other income to required they file taxes? If yes, and you would like us to file those for them, please list each child's name to which this pertains in the Comment field and we'll contact you for more info. | E25: Link to Q&A
D26: Can you be claimed as a dependent on someone else's return this year? (If yes, who's? Did they claim you?)
A27: Income
D28: Did you receive any disability income? (If yes, please include the W-2, 1099-G, or other document that captures this income)
D29: Did you receive any unemployment income? (If yes, please include the 1099-G)
D30: Did you receive any social security income? (If yes, please include the 1099-SSA)
D31: Did you pay or receive any alimony. (If yes, indicate pay or receive, how much, and the date on which your divorce was final - new for 2019 due to changed tax rules for the way alimony is handled after 12/31/18 - in Comment)
D32: Did you receive any interest from any financial institution? (If yes, please include the 1099-INT for that interest, or list the institutions and interest amounts in the comment field.) Note that a 1099-INT will only be issued if you received >= $10 from the institution and you may have to download it from their website
D33: Did you receive any dividends? (If yes, please include the 1099-DIV or Consolidated 1099-B showing those dividends). If you have brokerage accounts managed by PWA, indicate Yes to this question with "Schwab" in the comment, because dividends have definitely been earned by your account. No form is needed. PWA has access to all Schwab tax docs.
D34: Did you receive any gambling winnings? (If yes, include the amounts, and if applicable, the W-2G that you received. Also include any supporting documentation if you're claiming offsetting gambling losses) | E34: Link to Gambling Tax Rules
D35: Did you receive any rental or royalty income? (If yes, please download and complete a Rental Property Income & Expense Summary xls or pdf from the Tax Prep Documents section of our website). Link Here -------------------------------------------------------> | E35: Link to Rental Worksheet
D36: Did you receive any 1099-MISC, 1099-NEC, 1099-K, or have any other self-employment income? (If yes, please include any 1099-MISC, 1099-NEC, 1099-K, and indicate "No Expenses" in the Comment field or complete a Small Business Income & Expense Summary xls or pdf from the Tax Prep Documents section of our website) Link Here -------------------------------------------------------> | E36: Link to Business Worksheet
D37: Did you receive or do you expect to receive a K-1 for income related to a partnership, S-Corp, or trust in which you own a share? (If yes, and you have received the K-1, please include it with your tax documents. If you expect it but have not received it, indicate "Yes" and list the entity name in the comment field.)
D38: Did you receive any unreported tip income? (If yes, indicate total amount in Comment.)
D39: Did you receive any tip income that qualifies for the "No Tax On Tips" deduction? | E39: Link
D40: Did you receive any overtime that qualifies for the "No Tax On Overtime" deduction? | E40: Link
D41: Did you have any foreign income or pay any foreign taxes other than on PWA-managed investment accounts? (If yes, please provide a summary of income earned by source country for each person in the household as well as taxes paid to each country).
D42: Did you receive any other income not mentioned above or do you have any other relevant income information to send / disclose?
A43: Retirement Plans
D44: Did you receive a distribution from a retirement plan (401(k), IRA, Roth IRA, Education IRA, SEP, SIMPLE, Profit Sharing Plan, etc.) including rollovers? (If yes, please include the 1099-R showing the distribution)
D45: Did you receive a distribution from an insurance policy or annuity? (If yes, please include the 1099-R showing the distribution)
D46: Did you convert part or all of your 401K, Traditional IRA, SEP IRA, or SIMPLE IRA to a Roth 401K or Roth IRA? (If yes, please include the 1099-R showing the distribution unless the converted account is PWA managed and at TDAmeritrade or Schwab… we have access to those)
D47: Did you transfer or roll over any amount from one retirement plan to another retirement plan? (If yes, please include the 1099-R showing the distribution)
D48: Did you contribute to a retirement plan (401(k), IRA, Roth IRA, Education IRA, SEP, SIMPLE, Profit Sharing Plan, etc.)? (If yes, indicate which in Comment)
D49: If you own a business and you qualify to do so, do you want to contribute to a self-employed retirement plan (e.g. solo-401k, SEP, SIMPLE, etc.)? If yes, we'll contact you to discuss.
D50: If you qualify to contribute to a Traditional IRA or Roth IRA and you haven't already, do you want to?
A51: Purchases / Sales / Real Estate / Debt
D52: Did you sell any stocks, bonds or other investment property? (If yes, please include the 1099-B, or Composite 1099 from your broker or other documentation showing sale price, acquisition cost, and acquisition date. Note, if the account is PWA managed at Schwab, no need to send anything... we have access online, but still check "Yes" and indicate "Schwab").
D53: At any time during 2025, did you: (a) receive (as a reward, award, or payment for property or services); or (b) sell, exchange, or otherwise dispose of a digital asset (or a financial interest in a digital asset)? Please note, this question now appears on your official tax forms from the IRS (and was broadened to include all dgital assets, like NFTs, in 2022). If yes, please provide details for each sell / exchange transaction including the date of sale, value of sale in USD, date of corrseponding purchase, and value of corresponding purchase in USD. Include Form 1099-DA (new for 2025) if received. Note that any spend of digital currencies or transfer of one digital currency to another (voluntary or "air dropped" is treated as a sale (i.e. if you bought something directly in bitcoin, it's treated as a sale of bitcoin)).
D54: Did you acquire, sell, or participate in a program involving your employer stock, other than a 401k (e.g RSUs, ESPP, Options, etc.)? (If yes, provide any documentation you received for the transactions. We will follow up for more information)
D55: Did you purchase, sell, or refinance your principal home or second home, or did you take a home equity loan? (If yes, please include the Settlement Statement / Closing Disclosure for the transacation))
D56: Did you buy or sell a rental property? (If yes, please include the Settlement Statement / Closing Disclosure for the transacation)
D57: Did you start a business or farm, purchase rental or royalty property, or acquire an interest in a partnership, S-Corporation, Trust, or REMIC? (If yes, indicate type of business in Comment)
D58: Did you purchase or dispose of any business assets (furniture, equipment, vehicles, real estate, etc.), or convert any personal assets to business use or business assets to personal use? (If yes, please provide a list of assets and what happened to them)
D59: Were you involved in bankruptcy, foreclosure, short sale, repossession, or had any debt (including credit cards, or student loans) cancelled? (If yes, please include the 1099-C if you received one for the transaction)
D60: Did you make an investment in a Qualified Opportunity Zone (QOZ) or participate in a tax-free exchange of real estate (1031 exchange)?
D61: Did anyone owe you money which had become uncollectible?
D62: Did you make any energy efficient improvements to your primary home that qualify for a tax credit? If yes, please provide a list of improvements and proof of the amount(s) spent. Note, all of these credits have terminated as of the end of 2025. | E62: Link to Energy Star | F62: Link to IRS Info
D63: Do you qualify for any other tax credits for any purchases that you made (e.g. Electric Vehicle)? (If yes, please provide the bill of sale and any other relevant information). Note that the EV credit changed dramatically for 2023 and then ended permanently on 9/30/2025. See link to the right for additional details. | E63: Link to EV Credit Info
D64: Did you purchase a new vehicle, boat, or aircraft? (If yes, please provide the purchase confirmation / receipt showing any sales tax paid)
A65: Adjustments
D66: Are you a teacher? If yes, indicate the amount spent (up to $300) on items for your classroom which were not reimbursed.
D67: Did you have a health savings account ("HSA")? (Note, this is different from a flexible spending account ("FSA") and different from a Health Reimbursement Account ("HRA")). If yes, list any amount that you contributed to the HSA out-of-pocket for the tax year (excludes all employer contributions and all contributions made through payroll). Include form 5498SA from the HSA provider, if avaialble (some aren't produced until May) and, if you withdrew any money from the HSA during the year, include form 1099SA (required) as well.
D68: If you had a high-deductible health plan and qualify to make a contribution to a Health Savings Account (HSA) (i.e. you did not max out already for the tax year), do you want to make a contributions? This is highly recommended given that contributions carry over indefinitely, are tax deductible on the way in, and tax-free on the way out if used to pay for medical expenses, even if you no longer have a HDHP at the time of payment.
D69: Did you incur moving expenses due to a change of employment? (If yes, please complete the Moving Expense Worksheet. Note that moving expenses are no longer deductible for Federal tax, but may still be deductible for State tax. Link Here: ------------------------> | E69: Link to Moving Expense Wksht
D70: Did you pay any student loan interest? (If yes, please include the 1098-E showing the amount paid)
A71: Deductions
A72: Please note that as of 2025, for Federal purposes, the maximum amount of state/local tax that can be deducted (previously $10k) is now capped at $40k (for both singles and married filing jointly) if income is < $500k. If income is > $600k, it is still capped at $10k. Between $500-600k, the max deduction is between $10-40k. This means many more people, esp those that pay property taxes and/or live in high state income tax states will now itemize. If you know that you will still not be able to itemize and that no itemized deductions could help your state taxes either, please indicate that in the first question below. This is not recommended. We'd much rather have all your tax documents and potential deductions and calculate it for you! The Federal standard deduction for 2025 is $ 15,750 Single, $23,625 Head of Household, and $31,500 Married Filing Jointly.
D73: Are you certain that you WILL NOT itemize deductions this year for both Federal and State tax purposes? If yes, check the Yes box and you can skip all other questions in this section.
D74: Did you incur a loss because of property damaged or destroyed in a Federal declared disaster? If yes, please list the disaster. We will contact you for more information.
D75: Did you pay medical costs (including COBRA premiums, but excluding all other insurance premiums) that may have exceeded 7.5% of your gross income for the year? If yes, please provide details and the total amount spend. Exclude anything that was reimbursed by insurance or a FSA/HRA/HSA.
D76: Did you pay for auto registration / tags in a state where the payment amount is based on the value of the vehicle? (If yes, please include receipt or deductible amount… note that you have to subtract $35 from the Registration Tax paid for each vehicle in MN and you can only use the VLF portion of the amount paid in CA). See web reference Here: -> | E76: Link to state info from Intuit
D77: Did you pay any mortgage interest on a residence or second home? If yes, please include the form 1098 received from your mortgage company. If you own mulitple homes, please indicate which 1098 goes with which home.
D78: Did any of the mortgage interest in the previous question come from a home equity loan / home equity line of credit / cash-out refinancing, where the loan proceeds were used for purposes other than to buy, build, or substantially improve your home?
D79: Did you pay any mortgage insurance premiums ("PMI", "MIP", "up-front MIP") on a residence or second home? If yes, please include the form 1098 received from your mortgage company or provide the amount you paid in mortgage insurance for the year for each home in the comments.
D80: Did you pay any property taxes for a residence, second home, plot of land, or any other non-rental property? If yes, indicate how much by property unless it's paid through escrow and shown on the 1098 for your mortgage. Note, the municipal tax year of the property tax bill is not relevant. Only count taxes actually paid in this calendar year. For this reason, uploading tax bills does not help unless you include the date they were paid.
D81: Did you make any charitable contributions? If yes, please fill out the CharitableContributions tab in this worksheet. You must fill it out in full. Leaving boxes blank will just lead to an email asking for the missing information. Alternative formats are ok, but must provide a list of all cash contributions (org, date, amount) and non-cash contributions (org, org address, date, description, amount, how acquired, and what method you used to value the items) either way
D82: Do you have a Donor Advised Fund (DAF)? (Most people don't… you'd know if you do). If yes, make sure you include contributions to the DAF as charitable contributions on the previous line but exclude grants made from the DAF from charitable contributions on the previous line.
D83: Did you incur any out-of-pocket unreimbursed expenses for charity? If yes, provide the total expense by date by charitable organization with your tax documents.
D84: Did you drive your owned car for charitable purpose and keep a mileage log? If yes, provide the total miles by date by charitable organization with your tax documents.
D85: Did you pay into a long-term care insurance contract? If yes, how much? Note: Long Term Care is different from Long-Term Disability Insurance.
D86: Did you use your car on the job as an employee, other than commuting to and from work? If yes, please provide a mileage worksheet with the year/make/model of car, when it was first used for business, what the starting and ending mileage are for the year, and the total business miles driven. Note that employee mileage is no longer deductible for Federal tax, but may be deductible for state tax. For self-employed mileage, please use the Business Worksheet referenced above in the Income section.
D87: Did you maintain a portion of your residence exclusively as an office? If yes, AND: 1) you are self-employed AND use the office space exclusively as an office for your business, check Yes and enter home office info on the Business Worksheet referenced in the Income section. 2) you are an employee AND use the office space exclusively as an office for your job, AND do so for the convenience of your employer (i.e. not because you choose to work from home sometimes), check Yes, include "Employee" in the Comment field and we will contact you for more information. Note that home office deductions for employees are no longer allowed for Federal tax, but may still be allowed for state tax depending on your home state.
D88: Do you pay any other costs to do your job that were not reimbursed by your employer? Note that these are no longer deductible for Federal tax, but may be deductible for state tax.
D89: Did you incur any other miscellaneous deductible items? Note that these are no longer deductible for Federal tax, but may be deductible for state tax. See Link Here for more info: ------------------> | E89: Link to IRS Misc Ded
A90: Education
D91: Did you receive a distribution from an Education Savings Account, 529 Plan, or other Qualified Tuition Program? (If yes, please include the 1099-Q from the plan, the corresponding 1098-T from the educational institution, and a statement of the student's account from the university's financial website showing all charges / payments during the tax year as some qualified expenses are not shown on the 1098-T.)
D92: Did you, your spouse, or a dependent incur any tuition expenses that are required to attend a college, university, or vocational school? (If yes, please include the 1098-T and a statement of the student's account from the university's financial website showing all charges / payments during the tax year as some qualified expenses are not shown on the 1098-T.))
D93: Did you make a contribution to a 529 Plan? (If yes, please list the amount by beneficiary or provide the relevant account statement)
D94: Did you make a contribution to an Educational Savings Account (this is not a 529 plan)? If yes, indicate how much and to what plan in Comment.
A95: Misc
D96: Do you owe any "use tax" to your resident state? Use tax is generally due when you purchase goods from outside the state and bring them in or purchase them in a way that sales tax is not collected (e.g. some internet sites). If you do owe use tax, most states allow you to provide an itemized list, or opt to use a lookup table based on income and zip code. If you answer yes to this question, please indicate "Itemized List" or "Lookup Table" in the comment field. If you choose "Itemized List" provide the list with your tax docs (date of purchase, vendor, description, amount paid).
D97: Did you have an interest in or signature or other authority over a financial account in a foreign country, such as a bank account, securities account, or other financial account whose account balance exceeded $10,000 USD at any point during the year?
D98: Did you have an interest in or any authority over any foreign accounts or assets held in foreign financial institutions that exceeded $50,000 USD at any point during the year?
D99: During the tax year, did you receive any gifts (cash or property) from a non-resident alien?
D100: Did you receive a distribution from, or were you the grantor of, or transferor to, a foreign trust?
...

Sheet CharitableContributions
A1: For Cash Contributions:
B2: Name of Charity | C2: Amount of Contribution | D2: Comment
A3: 1
A4: 2
A5: 3
A6: 4
A7: 5
A8: 6
A9: 7
A10: 8
A11: 9
A12: 10
A13: 11
A14: 12
B15: TOTAL | C15: =SUM(C3:C14) -> 0
A17: For Non-Cash Contributions
B18: Name of Charity | C18: Fair Market Value of Donation (aggregate value of items in this donation) | D18: Address of Charity | E18: Brief Description of Items Donated (e.g. "Clothes, TV, Desk, Small Appliances"). Note: you are required to keep an itemized list of items donated and value assigned to each | F18: Date of Donation | G18: Date Acquired (Various is a valid answer) | H18: How Acquired | I18: Cost of acquisition OR adjusted basis (this cell only relevant if the item has appreciated since acquisition) | J18: How Valued | K18: Comment
A19: 1 | P19: Purchase | Q19: Appraisal
A20: 2 | P20: Gift | Q20: Average share price
A21: 3 | P21: Inheritance | Q21: Catalog
A22: 4 | P22: Exchange | Q22: Comp Sales
A23: 5 | P23: Created | Q23: Thrift Shop Value
A24: 6 | Q24: Consignment Shop Value
A25: 7
A26: 8
A27: 9
A28: 10
A29: 11
A30: 12
B31: TOTAL | C31: =SUM(C19:C30) -> 0
A33: Sample Non-Cash Contribution Info - This is how you should fill out the above
B34: Name of Charity | C34: Fair Market Value of Donation (aggregate value of items in this donation) | D34: Address of Charity | E34: Brief Description of Items Donated (e.g. "Clothes, TV, Desk, Small Appliances"). Note: you are required to keep an itemized list of items donated and value assigned to each | F34: Date of Donation | G34: Date Acquired (Various is a valid answer) | H34: How Acquired | I34: Cost of acquisition OR adjusted basis (this cell only relevant if the item has appreciated since acquisition) | J34: How Valued | K34: Comment
A35: 1 | B35: Goodwill | C35: 565 | D35: 123 Main St., Anytown, XX, 99999 | E35: Baby clothes, small electronics | F35: 45061 | G35: Various | H35: Purchase | I35: N/A | J35: Thrift Shop Value | K35: Receipt attached

Sheet QualifiedChildcare
B1: Provider Info | F1: Amount Paid For Care For Each Child At This Provider
B2: Provider Name | C2: Provider Tax ID / SSN | D2: Provider Address | E2: Provider Phone | F2: =IF(PersonalInfo!B28="","",PersonalInfo!B28) | G2: =IF(PersonalInfo!C28="","",PersonalInfo!C28) | H2: =IF(PersonalInfo!B40="","",PersonalInfo!B40) | I2: =IF(PersonalInfo!C40="","",PersonalInfo!C40) | J2: =IF(PersonalInfo!B52="","",PersonalInfo!B52) | K2: =IF(PersonalInfo!C52="","",PersonalInfo!C52) | L2: =IF(PersonalInfo!B64="","",PersonalInfo!B64) | M2: =IF(PersonalInfo!C64="","",PersonalInfo!C64) | N2: Total All Children
A3: 1 | N3: =SUM(F3:M3) -> 0
A4: 2 | N4: =SUM(F4:M4) -> 0
A5: 3 | N5: =SUM(F5:M5) -> 0
A6: 4 | N6: =SUM(F6:M6) -> 0
B7: TOTAL ALL PROVIDERS | F7: =SUM(F3:F6) -> 0 | G7: =SUM(G3:G6) -> 0 | H7: =SUM(H3:H6) -> 0 | I7: =SUM(I3:I6) -> 0 | J7: =SUM(J3:J6) -> 0 | K7: =SUM(K3:K6) -> 0 | L7: =SUM(L3:L6) -> 0 | M7: =SUM(M3:M6) -> 0 | N7: =SUM(N3:N6) -> 0
B8: Note: You must enter comumn B, C, D, E, and the amount paid by child for each provider. Failure to provide the tax id, address, or phone will result in an email asking for this information. Please enter it here before submitting to avoid the back and forth.
B12: SAMPLE - this is how you should fill out the info above
B13: Provider Info | F13: Amount Paid For Care For Each Child At This Provider
B14: Provider Name | C14: Provider Tax ID / SSN | D14: Provider Address | E14: Provider Phone | F14: Child 1 | G14: Child 2 | H14: Child 3 | I14: =IF(PersonalInfo!C52="","",PersonalInfo!C52) | J14: =IF(PersonalInfo!B64="","",PersonalInfo!B64) | K14: =IF(PersonalInfo!C64="","",PersonalInfo!C64) | L14: =IF(PersonalInfo!B76="","",PersonalInfo!B76) | M14: =IF(PersonalInfo!C76="","",PersonalInfo!C76) | N14: Total All Children
A15: 1 | B15: ABC Childcare | C15: 12-3456789 | D15: 123 Main St., Anytown, ST, 98765 | E15: 555-555-1234 | F15: 14000 | G15: 2000 | N15: =SUM(F15:M15) -> 16000
A16: 2 | B16: XYZ Childcare | C16: 98-7654321 | D16: 987 1st Ave., Springfield, ZZ, 12345 | E16: 555-555-9876 | F16: 2000 | G16: 8000 | H16: 5000 | N16: =SUM(F16:M16) -> 15000
A17: 3 | N17: =SUM(F17:M17) -> 0
A18: 4 | N18: =SUM(F18:M18) -> 0
B19: TOTAL ALL PROVIDERS | F19: =SUM(F15:F18) -> 16000 | G19: =SUM(G15:G18) -> 10000 | H19: =SUM(H15:H18) -> 5000 | I19: =SUM(I15:I18) -> 0 | J19: =SUM(J15:J18) -> 0 | K19: =SUM(K15:K18) -> 0 | L19: =SUM(L15:L18) -> 0 | M19: =SUM(M15:M18) -> 0 | N19: =SUM(N15:N18) -> 31000

Sheet ChildTaxCredit
A1: The following are tax preparer due dilligence questions that must be answered by the taxpayer prior to filing for the Child Tax Credit
A2: Indicate yes/no response with 'x' in the appropriate cell. Provide additional detail in the Comment field as required for each question.
A3: Question | B3: Yes | C3: No | D3: Comment
A4: Can you provide documentation that shows that all of your children are your children, lived with you for more than half the year, and didn't provide more than half of their own support for the year (not asking you to provide it, just asking if you can provide it)?
A5: Did you ever claim the Child Tax Credit or Additional Child Tax Credit in a previous year only to have the IRS disallow your claim at a later date?
A6: Is there any other person who can claim your children as their dependent?
A7: Have you "released claim" for the Child Tax Credit or Additional Child Tax Credit to another person such as an ex-spouse?
A8: Are all children citizens of the US?
